x402_langchain/__init__.py
x402_langchain/agent.py
x402_langchain/client.py
x402_langchain/config.py
x402_langchain/enhanced_client.py
x402_langchain/exceptions.py
x402_langchain/logger.py
x402_langchain/mocking.py
x402_langchain/models.py
x402_langchain/shared/__init__.py
x402_langchain/shared/analytics.py
x402_langchain/shared/facilitator.py
x402_langchain/shared/wallet.py
x402_langchain/tools.py
x402_langchain-1.3.0.dist-info/METADATA
x402_langchain-1.3.0.dist-info/WHEEL
x402_langchain-1.3.0.dist-info/RECORD
