Metadata-Version: 2.1
Name: x402-langchain
Version: 1.3.0
Summary: x402 payment integration for LangChain - Enable autonomous AI agent payments
Home-page: https://github.com/x402/x402-langchain
License: MIT
Keywords: x402,langchain,ai-agents,payments,micropayments,blockchain
Author: x402 Team
Requires-Python: >=3.9,<4.0
Classifier: Development Status :: 4 - Beta
Classifier: Intended Audience :: Developers
Classifier: License :: OSI Approved :: MIT License
Classifier: Programming Language :: Python :: 3
Classifier: Programming Language :: Python :: 3.9
Classifier: Programming Language :: Python :: 3.10
Classifier: Programming Language :: Python :: 3.11
Classifier: Topic :: Scientific/Engineering :: Artificial Intelligence
Classifier: Topic :: Software Development :: Libraries :: Python Modules
Requires-Dist: aiohttp (>=3.8.0)
Requires-Dist: eth-account (>=0.10.0,<0.11.0)
Requires-Dist: httpx (>=0.25.0,<0.26.0)
Requires-Dist: langchain (>=0.1.0,<0.2.0)
Requires-Dist: langchain-core (>=0.1.0,<0.2.0)
Requires-Dist: pydantic (>=2.5.0,<3.0.0)
Requires-Dist: web3 (>=6.11.0,<7.0.0)
Project-URL: Repository, https://github.com/x402/x402-langchain
